Workbook

Sheet 2024
A1: COMPANY NAME | B1: YEAR | C1: HIGH | D1: LOW | E1: CLOSE | F1: VOLUME IN Cr | G1: GROWTH % | H1: SECTOR | I1: FII | J1: DII | K1: PUBLIC | L1: PROMOTERS | M1: MARKET CAP IN 2024(Cr) | N1: P/E Ratio (TIMES) | O1: EPS (Earnings Per Share) | P1: ROE (%) | Q1: Beta (β) | R1: SECTOR AVG PE | S1: REVENUE IN Cr (FY 2024) | T1: NET PROFIT IN Cr (FY-2024)
A2: Adani Enterprises Ltd. | B2: 2024 | C2: 3743 | D2: 2641.2 | E2: 3115.4 | F2: 48200 | G2: -0.024 | H2: Diversified | I2: 0.142 | J2: 0.0432 | K2: 0.0676 | L2: 0.7472 | M2: 355150 | N2: 86.2 | O2: 36.14 | P2: 0.114 | Q2: 1.85 | R2: 42.15 | S2: 108450 | T2: 4120
A3: Adani Ports and Special Economic Zone Ltd. | B3: 2024 | C3: 1607 | D3: 1145 | E3: 1485.65 | F3: 22500 | G3: 0.108 | H3: Infrastructure | I3: 0.1488 | J3: 0.125 | K3: 0.0672 | L3: 0.6589 | M3: 320950 | N3: 39.6 | O3: 37.52 | P3: 0.1542 | Q3: 1.35 | R3: 35.4 | S3: 26711 | T3: 8104
A4: Apollo Hospitals Enterprise Ltd. | B4: 2024 | C4: 7025 | D4: 4750 | E4: 6480.8 | F4: 12800 | G4: 0.182 | H4: Hospitals | I4: 0.4492 | J4: 0.1785 | K4: 0.079 | L4: 0.2933 | M4: 92710 | N4: 103.14 | O4: 62.54 | P4: 0.148 | Q4: 0.65 | R4: 44.2 | S4: 19056 | T4: 899
A5: Asian Paints Ltd. | B5: 2024 | C5: 3422 | D5: 2708 | E5: 2910 | F5: 15600 | G5: -0.085 | H5: Paints | I5: 0.1522 | J5: 0.1102 | K5: 0.2113 | L5: 0.5263 | M5: 279145 | N5: 51.13 | O5: 56.92 | P5: 0.331 | Q5: 0.62 | R5: 55.4 | S5: 35494 | T5: 5460
A6: Axis Bank Ltd. | B6: 2024 | C6: 1339.65 | D6: 1023 | E6: 1180.4 | F6: 28500 | G6: 0.124 | H6: Banking | I6: 0.5383 | J6: 0.2862 | K6: 0.0955 | L6: 0.08 | M6: 363905 | N6: 14.64 | O6: 80.64 | P6: 0.172 | Q6: 1.18 | R6: 12.5 | S6: 124650 | T6: 24861
A7: Bajaj Auto Ltd. | B7: 2024 | C7: 12774 | D7: 6554 | E7: 10850.5 | F7: 18400 | G7: 0.554 | H7: Automobile | I7: 0.1465 | J7: 0.1244 | K7: 0.1788 | L7: 0.5503 | M7: 298450 | N7: 40.12 | O7: 264.45 | P7: 0.252 | Q7: 0.58 | R7: 34.2 | S7: 44685 | T7: 7479
A8: Bajaj Finance Ltd. | B8: 2024 | C8: 8192 | D8: 6355 | E8: 7110 | F8: 32400 | G8: -0.025 | H8: Financial Services | I8: 0.2089 | J8: 0.1428 | K8: 0.1014 | L8: 0.5469 | M8: 432150 | N8: 30.5 | O8: 233.15 | P8: 0.221 | Q8: 1.24 | R8: 25.4 | S8: 54969 | T8: 14451
A9: Bajaj Finserv Ltd. | B9: 2024 | C9: 1974 | D9: 1419 | E9: 1745 | F9: 16800 | G9: 0.052 | H9: Financial Services | I9: 0.071 | J9: 0.0764 | K9: 0.2457 | L9: 0.6069 | M9: 278140 | N9: 34.15 | O9: 51.1 | P9: 0.158 | Q9: 1.08 | R9: 28.4 | S9: 110383 | T9: 8148
A10: Bharat Electronics Ltd. | B10: 2024 | C10: 340.5 | D10: 170.15 | E10: 295.2 | F10: 14200 | G10: 0.652 | H10: Defense Electronics | I10: 0.1743 | J10: 0.2423 | K10: 0.072 | L10: 0.5114 | M10: 205450 | N10: 53.7 | O10: 5.5 | P10: 0.244 | Q10: 1.21 | R10: 45.1 | S10: 19819 | T10: 4020
A11: Bharti Airtel Ltd. | B11: 2024 | C11: 1775 | D11: 980.1 | E11: 1620.4 | F11: 34200 | G11: 0.625 | H11: Telecom | I11: 0.245 | J11: 0.1845 | K11: 0.0375 | L11: 0.533 | M11: 955140 | N11: 120.4 | O11: 13.5 | P11: 0.122 | Q11: 0.82 | R11: 48.2 | S11: 149982 | T11: 7467
A12: Cipla Ltd. | B12: 2024 | C12: 1702 | D12: 1175 | E12: 1510.8 | F12: 14800 | G12: 0.224 | H12: Pharmaceuticals | I12: 0.2582 | J12: 0.2455 | K12: 0.1622 | L12: 0.3341 | M12: 121950 | N12: 29.48 | O12: 51.25 | P12: 0.175 | Q12: 0.55 | R12: 32.1 | S12: 25774 | T12: 4132
A13: Coal India Ltd. | B13: 2024 | C13: 543.55 | D13: 302.2 | E13: 485.4 | F13: 12500 | G13: 0.402 | H13: Mining | I13: 0.0842 | J13: 0.2335 | K13: 0.051 | L13: 0.6313 | M13: 299120 | N13: 8.05 | O13: 60.65 | P13: 0.5215 | Q13: 0.88 | R13: 12.4 | S13: 142324 | T13: 37369
... A25: Infosys Ltd. | B25: 2024 | C25: 1991.45 | D25: 1358.35 | E25: 1880.2 | F25: 24500 | G25: 0.225 | H25: IT Services | I25: 0.3412 | J25: 0.3545 | K25: 0.1572 | L25: 0.1471 | M25: 780500 | N25: 29.7 | O25: 63.3 | P25: 0.304 | Q25: 0.92 | R25: 31.5 | S25: 153670 | T25: 26233
A26: InterGlobe Aviation Ltd. | B26: 2024 | C26: 4610 | D26: 2920 | E26: 4380 | F26: 14200 | G26: 0.482 | H26: Aviation | I26: 0.2366 | J26: 0.1482 | K26: 0.0623 | L26: 0.5529 | M26: 169420 | N26: 20.65 | O26: 211.85 | P26: N/A | Q26: 1.24 | R26: 24.1 | S26: 68904 | T26: 8172
A27: JSW Steel Ltd. | B27: 2024 | C27: 1065.7 | D27: 760.3 | E27: 995.1 | F27: 12450 | G27: 0.284 | H27: Steel | I27: 0.2452 | J27: 0.1015 | K27: 0.2052 | L27: 0.4481 | M27: 242850 | N27: 27.18 | O27: 36.6 | P27: 0.1245 | Q27: 1.42 | R27: 18.5 | S27: 175006 | T27: 8938
A28: Jio Financial Services Ltd. | B28: 2024 | C28: 394.7 | D28: 221 | E28: 365.2 | F28: 28900 | G28: 0.425 | H28: Financial Services | I28: 0.1755 | J28: 0.142 | K28: 0.2113 | L28: 0.4712 | M28: 232040 | N28: 146.1 | O28: 2.5 | P28: 0.015 | Q28: 1.18 | R28: 28.4 | S28: 1855 | T28: 1605
A29: Kotak Mahindra Bank Ltd. | B29: 2024 | C29: 1947 | D29: 1530 | E29: 1875.4 | F29: 14800 | G29: 0.115 | H29: Banking | I29: 0.3764 | J29: 0.225 | K29: 0.1397 | L29: 0.2589 | M29: 372500 | N29: 27.05 | O29: 69.35 | P29: 0.148 | Q29: 1.05 | R29: 15.8 | S29: 62540 | T29: 13782
A30: Larsen & Toubro Ltd. | B30: 2024 | C30: 3948.6 | D30: 3210.15 | E30: 3820.4 | F30: 19500 | G30: 0.198 | H30: Engineering | I30: 0.2572 | J30: 0.3715 | K30: 0.3713 | L30: 0 | M30: 522140 | N30: 41.15 | O30: 92.85 | P30: 0.153 | Q30: 0.95 | R30: 38.4 | S30: 475000 | T30: 13059
A31: Mahindra & Mahindra Ltd. | B31: 2024 | C31: 3220 | D31: 1620.4 | E31: 3115.6 | F31: 22100 | G31: 0.852 | H31: Automobile | I31: 0.4015 | J31: 0.2642 | K31: 0.1411 | L31: 0.1932 | M31: 387420 | N31: 34.65 | O31: 90.65 | P31: 0.184 | Q31: 1.12 | R31: 22.8 | S31: 139078 | T31: 11269
A32: Maruti Suzuki India Ltd. | B32: 2024 | C32: 13397 | D32: 9770 | E32: 12150 | F32: 18600 | G32: 0.215 | H32: Automobile | I32: 0.2055 | J32: 0.152 | K32: 0.0606 | L32: 0.5819 | M32: 382100 | N32: 27.8 | O32: 437.2 | P32: 0.1685 | Q32: 0.88 | R32: 22.8 | S32: 140933 | T32: 13209
A33: Max Healthcare Institute Ltd. | B33: 2024 | C33: 1090 | D33: 650.4 | E33: 1045.75 | F33: 9800 | G33: 0.524 | H33: Healthcare | I33: 0.531 | J33: 0.152 | K33: 0.0795 | L33: 0.2375 | M33: 101520 | N33: 83.6 | O33: 12.5 | P33: 0.142 | Q33: 0.82 | R33: 45.2 | S33: 7214 | T33: 1215
A34: NTPC Ltd. | B34: 2024 | C34: 448.45 | D34: 290.1 | E34: 420.3 | F34: 11200 | G34: 0.356 | H34: Power Generation | I34: 0.1785 | J34: 0.269 | K34: 0.0415 | L34: 0.511 | M34: 407540 | N34: 19.1 | O34: 22 | P34: 0.138 | Q34: 0.85 | R34: 23.5 | S34: 176215 | T34: 21332
A35: Nestle India Ltd. | B35: 2024 | C35: 2770.75 | D35: 2242 | E35: 2610.3 | F35: 9450 | G35: 0.128 | H35: FMCG | I35: 0.121 | J35: 0.0915 | K35: 0.1599 | L35: 0.6276 | M35: 251680 | N35: 77.5 | O35: 33.65 | P35: 1.084 | Q35: 0.58 | R35: 48.2 | S35: 19121 | T35: 3245
A36: Oil & Natural Gas Corporation Ltd. | B36: 2024 | C36: 344.6 | D36: 201.2 | E36: 315.4 | F36: 16800 | G36: 0.542 | H36: Oil & Gas | I36: 0.091 | J36: 0.198 | K36: 0.1221 | L36: 0.5889 | M36: 396780 | N36: 6.95 | O36: 45.4 | P36: 0.141 | Q36: 0.92 | R36: 12.4 | S36: 643000 | T36: 57101
A37: Power Grid Corporation of India Ltd. | B37: 2024 | C37: 366.25 | D37: 230.15 | E37: 345.8 | F37: 10200 | G37: 0.445 | H37: Power Transmission | I37: 0.286 | J37: 0.1215 | K37: 0.0791 | L37: 0.5134 | M37: 321650 | N37: 20.65 | O37: 16.75 | P37: 0.182 | Q37: 0.78 | R37: 23.5 | S37: 45855 | T37: 15573
A38: Reliance Industries Ltd. | B38: 2024 | C38: 3217.1 | D38: 2550 | E38: 3015.4 | F38: 65800 | G38: 0.185 | H38: Oil & Gas / Telecom / Retail | I38: 0.221 | J38: 0.1655 | K38: 0.1102 | L38: 0.5033 | M38: 2040500 | N38: 29.25 | O38: 103 | P38: 0.095 | Q38: 1.08 | R38: 24.1 | S38: 914472 | T38: 69621
... A45: Tata Motors Passenger Vehicles Ltd. | B45: 2024 | C45: 1179.05 | D45: 780.4 | E45: 1045.3 | F45: 18450 | G45: 0.342 | H45: Automobile | I45: 0.192 | J45: 0.161 | K45: 0.1834 | L45: 0.4636 | M45: 345200 | N45: 12.4 | O45: 84.15 | P45: 0.315 | Q45: 1.45 | R45: 25.5 | S45: 437928 | T45: 31399
A46: Tata Steel Ltd. | B46: 2024 | C46: 184.6 | D46: 128.1 | E46: 172.3 | F46: 22100 | G46: 0.285 | H46: Steel | I46: 0.196 | J46: 0.234 | K46: 0.2381 | L46: 0.3319 | M46: 215400 | N46: N/A | O46: -3.53 | P46: -0.042 | Q46: 1.32 | R46: 15.2 | S46: 229171 | T46: -4409
A47: Tech Mahindra Ltd. | B47: 2024 | C47: 1789.6 | D47: 1209.4 | E47: 1706.2 | F47: 18450 | G47: 0.315 | H47: IT Services | I47: 0.242 | J47: 0.3074 | K47: 0.1005 | L47: 0.3501 | M47: 136296 | N47: 39.1 | O47: 26.71 | P47: 0.0889 | Q47: 0.95 | R47: 28.75 | S47: 53290 | T47: 2064
A48: Titan Company Ltd. | B48: 2024 | C48: 3886.95 | D48: 3055.2 | E48: 3612.4 | F48: 9200 | G48: 0.155 | H48: Consumer Goods | I48: 0.1855 | J48: 0.1045 | K48: 0.181 | L48: 0.529 | M48: 321450 | N48: 91.2 | O48: 39.38 | P48: 0.298 | Q48: 0.82 | R48: 82.5 | S48: 51084 | T48: 3496
A49: Trent Ltd. | B49: 2024 | C49: 8345 | D49: 2950.4 | E49: 7850.2 | F49: 15600 | G49: 1.6 | H49: Retail | I49: 0.278 | J49: 0.142 | K49: 0.2099 | L49: 0.3701 | M49: 278450 | N49: 188.5 | O49: 41.55 | P49: 0.264 | Q49: 0.88 | R49: 95.2 | S49: 12375 | T49: 1477
A50: UltraTech Cement Ltd. | B50: 2024 | C50: 12140 | D50: 9250.6 | E50: 11820.45 | F50: 6400 | G50: 0.228 | H50: Cement | I50: 0.172 | J50: 0.144 | K50: 0.0845 | L50: 0.5995 | M50: 342150 | N50: 48.7 | O50: 242.65 | P50: 0.128 | Q50: 0.84 | R50: 35.2 | S50: 70908 | T50: 7005
A51: Wipro Ltd. | B51: 2024 | C51: 580 | D51: 430.2 | E51: 562.1 | F51: 12500 | G51: 0.185 | H51: IT Services | I51: 0.065 | J51: 0.102 | K51: 0.1042 | L51: 0.7288 | M51: 294150 | N51: 26.4 | O51: 21.25 | P51: 0.158 | Q51: 0.85 | R51: 31.2 | S51: 89760 | T51: 11100

Sheet 2025
A1: COMPANY NAME | B1: YEAR | C1: HIGH | D1: LOW | E1: CLOSE | F1: VOLUME IN Cr | G1: GROWTH % | H1: SECTOR | I1: FII | J1: DII | K1: PUBLIC | L1: PROMOTERS | M1: MARKET CAP IN 2025 (Cr) | N1: P/E Ratio (TIMES) | O1: EPS (Earnings Per Share) | P1: ROE (%) | Q1: Beta (β) | R1: SECTOR AVG PE | S1: REVENUE IN Cr (FY 2025) | T1: NET PROFIT IN Cr (FY-2025)
A2: Adani Enterprises Ltd. | B2: 2025 | C2: 3743 | D2: 2530.6 | E2: 3120.45 | F2: 48200 | G2: 0.224 | H2: Diversified | I2: 0.1441 | J2: 0.0598 | K2: 0.0489 | L2: 0.7472 | M2: 3557.3 | N2: 109.68 | O2: 28.45 | P2: 0.0945 | Q2: 1.45 | R2: 45.2 | S2: 96420 | T2: 3240
A3: Adani Ports and Special Economic Zone Ltd. | B3: 2025 | C3: 1620 | D3: 1180 | E3: 1510.2 | F3: 22500 | G3: 0.283 | H3: Infrastructure | I3: 0.1522 | J3: 0.1145 | K3: 0.0744 | L3: 0.6589 | M3: 326200 | N3: 35.6 | O3: 42.42 | P3: 0.168 | Q3: 1.28 | R3: 28.4 | S3: 28450 | T3: 9150
A4: Apollo Hospitals Enterprise Ltd. | B4: 2025 | C4: 7450 | D4: 5680 | E4: 7120.45 | F4: 12800 | G4: 0.185 | H4: Hospitals | I4: 0.448 | J4: 0.171 | K4: 0.088 | L4: 0.293 | M4: 102380 | N4: 84.5 | O4: 84.26 | P4: 0.148 | Q4: 0.65 | R4: 45.2 | S4: 21350 | T4: 1212
A5: Asian Paints Ltd. | B5: 2025 | C5: 3485 | D5: 2740.2 | E5: 3115.4 | F5: 15600 | G5: 0.082 | H5: Paints | I5: 0.154 | J5: 0.1125 | K5: 0.2072 | L5: 0.5263 | M5: 298750 | N5: 52.4 | O5: 59.45 | P5: 0.268 | Q5: 0.78 | R5: 48.2 | S5: 38950 | T5: 5120
A6: Axis Bank Ltd. | B6: 2025 | C6: 1385 | D6: 1020.5 | E6: 1290.75 | F6: 28500 | G6: 0.154 | H6: Banking | I6: 0.538 | J6: 0.2845 | K6: 0.0975 | L6: 0.08 | M6: 398420 | N6: 14.2 | O6: 90.89 | P6: 0.1825 | Q6: 1.15 | R6: 18.5 | S6: 122450 | T6: 28140
A7: Bajaj Auto Ltd. | B7: 2025 | C7: 12480 | D7: 8950.5 | E7: 11850.4 | F7: 18400 | G7: 0.228 | H7: Automobile | I7: 0.142 | J7: 0.1015 | K7: 0.2059 | L7: 0.5506 | M7: 332450 | N7: 38.4 | O7: 308.6 | P7: 0.245 | Q7: 0.82 | R7: 32.5 | S7: 52140 | T7: 8650
A8: Bajaj Finance Ltd. | B8: 2025 | C8: 8150 | D8: 6240.2 | E8: 7680.5 | F8: 32400 | G8: 0.126 | H8: Financial Services | I8: 0.1825 | J8: 0.141 | K8: 0.1297 | L8: 0.5468 | M8: 465230 | N8: 32.4 | O8: 237.05 | P8: 0.231 | Q8: 1.22 | R8: 26.5 | S8: 58420 | T8: 14350
A9: Bajaj Finserv Ltd. | B9: 2025 | C9: 2045 | D9: 1510.5 | E9: 1890.75 | F9: 18250 | G9: 0.114 | H9: Financial Services | I9: 0.2685 | J9: 0.075 | K9: 0.1487 | L9: 0.6078 | M9: 301240 | N9: 36.2 | O9: 52.2 | P9: 0.148 | Q9: 1.12 | R9: 27.8 | S9: 118650 | T9: 9280
A10: Bharat Electronics Ltd. | B10: 2025 | C10: 395.4 | D10: 275.15 | E10: 382.6 | F10: 15800 | G10: 0.296 | H10: Defense Electronics | I10: 0.1785 | J10: 0.244 | K10: 0.066 | L10: 0.5115 | M10: 279650 | N10: 45.2 | O10: 8.45 | P10: 0.264 | Q10: 1.22 | R10: 38.4 | S10: 22140 | T10: 4280
A11: Bharti Airtel Ltd. | B11: 2025 | C11: 1840.5 | D11: 1450.2 | E11: 1765.8 | F11: 38450 | G11: 0.312 | H11: Telecom | I11: 0.251 | J11: 0.204 | K11: 0.0305 | L11: 0.5145 | M11: 985600 | N11: 72.1 | O11: 24.5 | P11: 0.168 | Q11: 0.82 | R11: 44.5 | S11: 164250 | T11: 12480
A12: Cipla Ltd. | B12: 2025 | C12: 1785.4 | D12: 1420.15 | E12: 1692.6 | F12: 15400 | G12: 0.184 | H12: Pharmaceuticals | I12: 0.2615 | J12: 0.245 | K12: 0.1575 | L12: 0.336 | M12: 136750 | N12: 30.15 | O12: 56.12 | P12: 0.172 | Q12: 0.58 | R12: 31.4 | S12: 28140 | T12: 4520
A13: Coal India Ltd. | B13: 2025 | C13: 565.4 | D13: 420.15 | E13: 532.8 | F13: 14200 | G13: 0.384 | H13: Mining | I13: 0.0825 | J13: 0.224 | K13: 0.0625 | L13: 0.631 | M13: 328400 | N13: 9.8 | O13: 54.3 | P13: 0.452 | Q13: 0.92 | R13: 12.5 | S13: 148650 | T13: 34250
... A51: Wipro Ltd. | B51: 2025 | C51: 273.1 | D51: 186.5 | E51: 265.4 | F51: 20430 | G51: 0.0588 | H51: IT Services | I51: 0.1049 | J51: 0.0838 | K51: 0.0838 | L51: 0.7263 | M51: 204314 | N51: 20.9 | O51: 12.54 | P51: 0.1699 | Q51: 0.88 | R51: 28.4 | S51: 89088 | T51: 13135

Sheet NIFTY 50 Smart Analysis
A1: COMPANY NAME | B1: Revenue Growth (2024-25) | C1: Profit Growth | D1: Price Growth | E1: FII Change | F1: DII Change | G1: Public Change | H1: Promoter Change | I1: Price vs Fundamental Check | J1: Total Growth Score | K1: Valuation Check | L1: Strong / Weak Company | M1: Momentum | N1: Investor Interest | O1: Final Rating | P1: Signal Type | Q1: Sector
A2: Adani Enterprises Ltd. | B2: =('2025'!S2 - '2024'!S2) / '2024'!S2 -> -0.11092669 | C2: =('2025'!T2 - '2024'!T2) / '2024'!T2 -> -0.21359223 | D2: =('2025'!E2 - '2024'!E2) / '2024'!E2 -> 0.0016209796 | E2: ='2025'!I2 - '2024'!I2 -> 0.0021 | F2: ='2025'!J2-'2024'!J2 -> 0.0166 | G2: ='2025'!K2-'2024'!K2 -> -0.0187 | H2: ='2025'!L2-'2024'!L2 -> 0 | I2: =IF(D2 > C2,"Overhyped","Fundamentally Strong") -> Overhyped | J2: =(B2 + C2 + D2)/3 -> -0.10763265 | K2: =IF('2025'!N2>'2025'!R2,"Overvalued","Undervalued") -> Overvalued | L2: =IF(AND(B2>0.15,C2>0.15),"Strong","Weak") -> Weak | M2: =IF(D2>0,"▲ Bullish","▼ Bearish") -> ▲ Bullish | N2: =IF(E2>0,"High Interest","Low Interest") -> High Interest | O2: =IF(AND(J2>0.2,'2025'!P2>0.15,'2025'!Q2<1.2),"Strong Buy", IF('NIFTY 50 Smart Analysis'!J2>0.1,"Buy","Avoid")) -> Avoid | P2: =IF(D3>0.1,"🟢BUY", IF(D3>0,"🟡HOLD", "🔴SELL")) -> 🟡HOLD | Q2: Diversified
A3: Adani Ports and Special Economic Zone Ltd. | B3: =('2025'!S3 - '2024'!S3) / '2024'!S3 -> 0.065104264 | C3: =('2025'!T3 - '2024'!T3) / '2024'!T3 -> 0.12907206 | D3: =('2025'!E3 - '2024'!E3) / '2024'!E3 -> 0.016524753 | E3: ='2025'!I3 - '2024'!I3 -> 0.0034 | F3: ='2025'!J3-'2024'!J3 -> -0.0105 | G3: ='2025'!K3-'2024'!K3 -> 0.0072 | H3: ='2025'!L3-'2024'!L3 -> 0 | I3: =IF(D3 > C3,"Overhyped","Fundamentally Strong") -> Fundamentally Strong | J3: =(B3 + C3 + D3)/3 -> 0.070233694 | K3: =IF('2025'!N3>'2025'!R3,"Overvalued","Undervalued") -> Overvalued | L3: =IF(AND(B3>0.15,C3>0.15),"Strong","Weak") -> Weak | M3: =IF(D3>0,"▲ Bullish","▼ Bearish") -> ▲ Bullish | N3: =IF(E3>0,"High Interest","Low Interest") -> High Interest | O3: =IF(AND(J3>0.2,'2025'!P3>0.15,'2025'!Q3<1.2),"Strong Buy", IF('NIFTY 50 Smart Analysis'!J3>0.1,"Buy","Avoid")) -> Avoid | P3: =IF(D4>0.1,"🟢BUY", IF(D4>0,"🟡HOLD", "🔴SELL")) -> 🟡HOLD | Q3: Infrastructure
A4: Apollo Hospitals Enterprise Ltd. | B4: =('2025'!S4 - '2024'!S4) / '2024'!S4 -> 0.12038203 | C4: =('2025'!T4 - '2024'!T4) / '2024'!T4 -> 0.34816463 | D4: =('2025'!E4 - '2024'!E4) / '2024'!E4 -> 0.098699235 | E4: ='2025'!I4 - '2024'!I4 -> -0.0012 | F4: ='2025'!J4-'2024'!J4 -> -0.0075 | G4: ='2025'!K4-'2024'!K4 -> 0.009 | H4: ='2025'!L4-'2024'!L4 -> -0.0003 | I4: =IF(D4 > C4,"Overhyped","Fundamentally Strong") -> Fundamentally Strong | J4: =(B4 + C4 + D4)/3 -> 0.18908196 | K4: =IF('2025'!N4>'2025'!R4,"Overvalued","Undervalued") -> Overvalued | L4: =IF(AND(B4>0.15,C4>0.15),"Strong","Weak") -> Weak | M4: =IF(D4>0,"▲ Bullish","▼ Bearish") -> ▲ Bullish | N4: =IF(E4>0,"High Interest","Low Interest") -> Low Interest | O4: =IF(AND(J4>0.2,'2025'!P4>0.15,'2025'!Q4<1.2),"Strong Buy", IF('NIFTY 50 Smart Analysis'!J4>0.1,"Buy","Avoid")) -> Buy | P4: =IF(D5>0.1,"🟢BUY", IF(D5>0,"🟡HOLD", "🔴SELL")) -> 🟡HOLD | Q4: Hospitals
A5: Asian Paints Ltd. | B5: =('2025'!S5 - '2024'!S5) / '2024'!S5 -> 0.097368569 | C5: =('2025'!T5 - '2024'!T5) / '2024'!T5 -> -0.062271062 | D5: =('2025'!E5 - '2024'!E5) / '2024'!E5 -> 0.070584192 | E5: ='2025'!I5 - '2024'!I5 -> 0.0018 | F5: ='2025'!J5-'2024'!J5 -> 0.0023 | G5: ='2025'!K5-'2024'!K5 -> -0.0041 | H5: ='2025'!L5-'2024'!L5 -> 0 | I5: =IF(D5 > C5,"Overhyped","Fundamentally Strong") -> Overhyped | J5: =(B5 + C5 + D5)/3 -> 0.035227233 | K5: =IF('2025'!N5>'2025'!R5,"Overvalued","Undervalued") -> Overvalued | L5: =IF(AND(B5>0.15,C5>0.15),"Strong","Weak") -> Weak | M5: =IF(D5>0,"▲ Bullish","▼ Bearish") -> ▲ Bullish | N5: =IF(E5>0,"High Interest","Low Interest") -> High Interest | O5: =IF(AND(J5>0.2,'2025'!P5>0.15,'2025'!Q5<1.2),"Strong Buy", IF('NIFTY 50 Smart Analysis'!J5>0.1,"Buy","Avoid")) -> Avoid | P5: =IF(D6>0.1,"🟢BUY", IF(D6>0,"🟡HOLD", "🔴SELL")) -> 🟡HOLD | Q5: Paints
A6: Axis Bank Ltd. | B6: =('2025'!S6 - '2024'!S6) / '2024'!S6 -> -0.017649418 | C6: =('2025'!T6 - '2024'!T6) / '2024'!T6 -> 0.13189333 | D6: =('2025'!E6 - '2024'!E6) / '2024'!E6 -> 0.093485259 | E6: ='2025'!I6 - '2024'!I6 -> -0.0003 | F6: ='2025'!J6-'2024'!J6 -> -0.0017 | G6: ='2025'!K6-'2024'!K6 -> 0.002 | H6: ='2025'!L6-'2024'!L6 -> 0 | I6: =IF(D6 > C6,"Overhyped","Fundamentally Strong") -> Fundamentally Strong | J6: =(B6 + C6 + D6)/3 -> 0.069243056 | K6: =IF('2025'!N6>'2025'!R6,"Overvalued","Undervalued") -> Undervalued | L6: =IF(AND(B6>0.15,C6>0.15),"Strong","Weak") -> Weak | M6: =IF(D6>0,"▲ Bullish","▼ Bearish") -> ▲ Bullish | N6: =IF(E6>0,"High Interest","Low Interest") -> Low Interest | O6: =IF(AND(J6>0.2,'2025'!P6>0.15,'2025'!Q6<1.2),"Strong Buy", IF('NIFTY 50 Smart Analysis'!J6>0.1,"Buy","Avoid")) -> Avoid | P6: =IF(D7>0.1,"🟢BUY", IF(D7>0,"🟡HOLD", "🔴SELL")) -> 🟡HOLD | Q6: Banking
A7: Bajaj Auto Ltd. | B7: =('2025'!S7 - '2024'!S7) / '2024'!S7 -> 0.16683451 | C7: =('2025'!T7 - '2024'!T7) / '2024'!T7 -> 0.15657173 | D7: =('2025'!E7 - '2024'!E7) / '2024'!E7 -> 0.092152435 | E7: ='2025'!I7 - '2024'!I7 -> -0.0045 | F7: ='2025'!J7-'2024'!J7 -> -0.0229 | G7: ='2025'!K7-'2024'!K7 -> 0.0271 | H7: ='2025'!L7-'2024'!L7 -> 0.0003 | I7: =IF(D7 > C7,"Overhyped","Fundamentally Strong") -> Fundamentally Strong | J7: =(B7 + C7 + D7)/3 -> 0.13851956 | K7: =IF('2025'!N7>'2025'!R7,"Overvalued","Undervalued") -> Overvalued | L7: =IF(AND(B7>0.15,C7>0.15),"Strong","Weak") -> Strong | M7: =IF(D7>0,"▲ Bullish","▼ Bearish") -> ▲ Bullish | N7: =IF(E7>0,"High Interest","Low Interest") -> Low Interest | O7: =IF(AND(J7>0.2,'2025'!P7>0.15,'2025'!Q7<1.2),"Strong Buy", IF('NIFTY 50 Smart Analysis'!J7>0.1,"Buy","Avoid")) -> Buy | P7: =IF(D8>0.1,"🟢BUY", IF(D8>0,"🟡HOLD", "🔴SELL")) -> 🟡HOLD | Q7: Automobile
A8: Bajaj Finance Ltd. | B8: =('2025'!S8 - '2024'!S8) / '2024'!S8 -> 0.06278084 | C8: =('2025'!T8 - '2024'!T8) / '2024'!T8 -> -0.0069891357 | D8: =('2025'!E8 - '2024'!E8) / '2024'!E8 -> 0.0802391 | E8: ='2025'!I8 - '2024'!I8 -> -0.0264 | F8: ='2025'!J8-'2024'!J8 -> -0.0018 | G8: ='2025'!K8-'2024'!K8 -> 0.0283 | H8: ='2025'!L8-'2024'!L8 -> -0.0001 | I8: =IF(D8 > C8,"Overhyped","Fundamentally Strong") -> Overhyped | J8: =(B8 + C8 + D8)/3 -> 0.045343601 | K8: =IF('2025'!N8>'2025'!R8,"Overvalued","Undervalued") -> Overvalued | L8: =IF(AND(B8>0.15,C8>0.15),"Strong","Weak") -> Weak | M8: =IF(D8>0,"▲ Bullish","▼ Bearish") -> ▲ Bullish | N8: =IF(E8>0,"High Interest","Low Interest") -> Low Interest | O8: =IF(AND(J8>0.2,'2025'!P8>0.15,'2025'!Q8<1.2),"Strong Buy", IF('NIFTY 50 Smart Analysis'!J8>0.1,"Buy","Avoid")) -> Avoid | P8: =IF(D9>0.1,"🟢BUY", IF(D9>0,"🟡HOLD", "🔴SELL")) -> 🟡HOLD | Q8: Financial Services
A9: Bajaj Finserv Ltd. | B9: =('2025'!S9 - '2024'!S9) / '2024'!S9 -> 0.074893779 | C9: =('2025'!T9 - '2024'!T9) / '2024'!T9 -> 0.1389298 | D9: =('2025'!E9 - '2024'!E9) / '2024'!E9 -> 0.083524355 | E9: ='2025'!I9 - '2024'!I9 -> 0.1975 | F9: ='2025'!J9-'2024'!J9 -> -0.0014 | G9: ='2025'!K9-'2024'!K9 -> -0.097 | H9: ='2025'!L9-'2024'!L9 -> 0.0009 | I9: =IF(D9 > C9,"Overhyped","Fundamentally Strong") -> Fundamentally Strong | J9: =(B9 + C9 + D9)/3 -> 0.099115978 | K9: =IF('2025'!N9>'2025'!R9,"Overvalued","Undervalued") -> Overvalued | L9: =IF(AND(B9>0.15,C9>0.15),"Strong","Weak") -> Weak | M9: =IF(D9>0,"▲ Bullish","▼ Bearish") -> ▲ Bullish | N9: =IF(E9>0,"High Interest","Low Interest") -> High Interest | O9: =IF(AND(J9>0.2,'2025'!P9>0.15,'2025'!Q9<1.2),"Strong Buy", IF('NIFTY 50 Smart Analysis'!J9>0.1,"Buy","Avoid")) -> Avoid | P9: =IF(D10>0.1,"🟢BUY", IF(D10>0,"🟡HOLD", "🔴SELL")) -> 🟢BUY | Q9: Financial Services
A10: Bharat Electronics Ltd. | B10: =('2025'!S10 - '2024'!S10) / '2024'!S10 -> 0.11710984 | C10: =('2025'!T10 - '2024'!T10) / '2024'!T10 -> 0.064676617 | D10: =('2025'!E10 - '2024'!E10) / '2024'!E10 -> 0.29607046 | E10: ='2025'!I10 - '2024'!I10 -> 0.0042 | F10: ='2025'!J10-'2024'!J10 -> 0.0017 | G10: ='2025'!K10-'2024'!K10 -> -0.006 | H10: ='2025'!L10-'2024'!L10 -> 0.0001 | I10: =IF(D10 > C10,"Overhyped","Fundamentally Strong") -> Overhyped | J10: =(B10 + C10 + D10)/3 -> 0.15928564 | K10: =IF('2025'!N10>'2025'!R10,"Overvalued","Undervalued") -> Overvalued | L10: =IF(AND(B10>0.15,C10>0.15),"Strong","Weak") -> Weak | M10: =IF(D10>0,"▲ Bullish","▼ Bearish") -> ▲ Bullish | N10: =IF(E10>0,"High Interest","Low Interest") -> High Interest | O10: =IF(AND(J10>0.2,'2025'!P10>0.15,'2025'!Q10<1.2),"Strong Buy", IF('NIFTY 50 Smart Analysis'!J10>0.1,"Buy","Avoid")) -> Buy | P10: =IF(D11>0.1,"🟢BUY", IF(D11>0,"🟡HOLD", "🔴SELL")) -> 🟡HOLD | Q10: Defense Electronics
A11: Bharti Airtel Ltd. | B11: =('2025'!S11 - '2024'!S11) / '2024'!S11 -> 0.095131416 | C11: =('2025'!T11 - '2024'!T11) / '2024'!T11 -> 0.67135396 | D11: =('2025'!E11 - '2024'!E11) / '2024'!E11 -> 0.089730931 | E11: ='2025'!I11 - '2024'!I11 -> 0.006 | F11: ='2025'!J11-'2024'!J11 -> 0.0195 | G11: ='2025'!K11-'2024'!K11 -> -0.007 | H11: ='2025'!L11-'2024'!L11 -> -0.0185 | I11: =IF(D11 > C11,"Overhyped","Fundamentally Strong") -> Fundamentally Strong | J11: =(B11 + C11 + D11)/3 -> 0.28540543 | K11: =IF('2025'!N11>'2025'!R11,"Overvalued","Undervalued") -> Overvalued | L11: =IF(AND(B11>0.15,C11>0.15),"Strong","Weak") -> Weak | M11: =IF(D11>0,"▲ Bullish","▼ Bearish") -> ▲ Bullish | N11: =IF(E11>0,"High Interest","Low Interest") -> High Interest | O11: =IF(AND(J11>0.2,'2025'!P11>0.15,'2025'!Q11<1.2),"Strong Buy", IF('NIFTY 50 Smart Analysis'!J11>0.1,"Buy","Avoid")) -> Strong Buy | P11: =IF(D12>0.1,"🟢BUY", IF(D12>0,"🟡HOLD", "🔴SELL")) -> 🟢BUY | Q11: Telecom
A12: Cipla Ltd. | B12: =('2025'!S12 - '2024'!S12) / '2024'!S12 -> 0.091797936 | C12: =('2025'!T12 - '2024'!T12) / '2024'!T12 -> 0.093901258 | D12: =('2025'!E12 - '2024'!E12) / '2024'!E12 -> 0.1203336 | E12: ='2025'!I12 - '2024'!I12 -> 0.0033 | F12: ='2025'!J12-'2024'!J12 -> -0.0005 | G12: ='2025'!K12-'2024'!K12 -> -0.0047 | H12: ='2025'!L12-'2024'!L12 -> 0.0019 | I12: =IF(D12 > C12,"Overhyped","Fundamentally Strong") -> Overhyped | J12: =(B12 + C12 + D12)/3 -> 0.10201093 | K12: =IF('2025'!N12>'2025'!R12,"Overvalued","Undervalued") -> Undervalued | L12: =IF(AND(B12>0.15,C12>0.15),"Strong","Weak") -> Weak | M12: =IF(D12>0,"▲ Bullish","▼ Bearish") -> ▲ Bullish | N12: =IF(E12>0,"High Interest","Low Interest") -> High Interest | O12: =IF(AND(J12>0.2,'2025'!P12>0.15,'2025'!Q12<1.2),"Strong Buy", IF('NIFTY 50 Smart Analysis'!J12>0.1,"Buy","Avoid")) -> Buy | P12: =IF(D13>0.1,"🟢BUY", IF(D13>0,"🟡HOLD", "🔴SELL")) -> 🟡HOLD | Q12: Pharmaceuticals
A13: Coal India Ltd. | B13: =('2025'!S13 - '2024'!S13) / '2024'!S13 -> 0.044447879 | C13: =('2025'!T13 - '2024'!T13) / '2024'!T13 -> -0.083464904 | D13: =('2025'!E13 - '2024'!E13) / '2024'!E13 -> 0.097651422 | E13: ='2025'!I13 - '2024'!I13 -> -0.0017 | F13: ='2025'!J13-'2024'!J13 -> -0.0095 | G13: ='2025'!K13-'2024'!K13 -> 0.0115 | H13: ='2025'!L13-'2024'!L13 -> -0.0003 | I13: =IF(D13 > C13,"Overhyped","Fundamentally Strong") -> Overhyped | J13: =(B13 + C13 + D13)/3 -> 0.019544799 | K13: =IF('2025'!N13>'2025'!R13,"Overvalued","Undervalued") -> Undervalued | L13: =IF(AND(B13>0.15,C13>0.15),"Strong","Weak") -> Weak | M13: =IF(D13>0,"▲ Bullish","▼ Bearish") -> ▲ Bullish | N13: =IF(E13>0,"High Interest","Low Interest") -> Low Interest | O13: =IF(AND(J13>0.2,'2025'!P13>0.15,'2025'!Q13<1.2),"Strong Buy", IF('NIFTY 50 Smart Analysis'!J13>0.1,"Buy","Avoid")) -> Avoid | P13: =IF(D14>0.1,"🟢BUY", IF(D14>0,"🟡HOLD", "🔴SELL")) -> 🟡HOLD | Q13: Mining
... A51: Wipro Ltd. | B51: =('2025'!S51 - '2024'!S51) / '2024'!S51 -> -0.007486631 | C51: =('2025'!T51 - '2024'!T51) / '2024'!T51 -> 0.18333333 | D51: =('2025'!E51 - '2024'!E51) / '2024'!E51 -> -0.52784202 | E51: ='2025'!I51 - '2024'!I51 -> 0.0399 | F51: ='2025'!J51-'2024'!J51 -> -0.0182 | G51: ='2025'!K51-'2024'!K51 -> -0.0204 | H51: ='2025'!L51-'2024'!L51 -> -0.0025 | I51: =IF(D51 > C51,"Overhyped","Fundamentally Strong") -> Fundamentally Strong | J51: =(B51 + C51 + D51)/3 -> -0.11733177 | K51: =IF('2025'!N51>'2025'!R51,"Overvalued","Undervalued") -> Undervalued | L51: =IF(AND(B51>0.15,C51>0.15),"Strong","Weak") -> Weak | M51: =IF(D51>0,"▲ Bullish","▼ Bearish") -> ▼ Bearish | N51: =IF(E51>0,"High Interest","Low Interest") -> High Interest | O51: =IF(AND(J51>0.2,'2025'!P51>0.15,'2025'!Q51<1.2),"Strong Buy", IF('NIFTY 50 Smart Analysis'!J51>0.1,"Buy","Avoid")) -> Avoid | P51: =IF(D52>0.1,"🟢BUY", IF(D52>0,"🟡HOLD", "🔴SELL")) -> 🔴SELL | Q51: IT Services

Sheet Sector Analysis
A1: Row Labels | B1: Average of Total Growth Score
A2: Automobile | B2: 0.11411525
A3: Clarify | B3: 0.48348197
A4: Consumer Goods | B4: 0.089689613
A5: Defense Electronics | B5: 0.15928564
A6: FMCG | B6: 0.07761295
A7: Hospitals | B7: 0.18908196
A8: Insurance | B8: 0.61376535
A9: IT Services | B9: 0.095273383
A10: Oil & Gas / Telecom / Retail | B10: 0.12413379
A11: Telecom | B11: 0.28540543
A12: Grand Total | B12: 0.17800019

Sheet DASHBOARD
A1: COMPANY NAME | B1: Revenue Growth (2024-25) | C1: Profit Growth | D1: Price Growth | E1: FII Change | F1: DII Change | G1: Public Change | H1: Promoter Change | I1: Price vs Fundamental Check | J1: Total Growth Score | K1: Valuation Check | L1: Strong / Weak Company | M1: Momentum | N1: Investor Interest | O1: Final Rating | P1: Signal Type | Q1: Sector
A2: Bharat Electronics Ltd. | B2: {=VLOOKUP(A2,'NIFTY 50 Smart Analysis'!A1:P51,{2,3,4,5,6,7,8,9,10,11,12,13,14,15,16},0)} -> 0.11710984 | C2: 0.064676617 | D2: 0.29607046 | E2: 0.0042 | F2: 0.0017 | G2: -0.006 | H2: 0.0001 | I2: Overhyped | J2: 0.15928564 | K2: Overvalued | L2: Weak | M2: ▲ Bullish | N2: High Interest | O2: Buy | P2: 🟡HOLD | Q2: =VLOOKUP(A2,'NIFTY 50 Smart Analysis'!A1:Q51,17,0) -> Defense Electronics
K7: Price vs Fundamental Check | L7: =VLOOKUP(A2,A1:P2,9,0) -> Overhyped
K8: Total Growth Score | L8: =VLOOKUP(A2,A2:P3,10,0) -> 0.15928564
K9: Valuation Check | L9: =VLOOKUP(A2,A1:P2,11,0) -> Overvalued
K10: Strong / Weak Company | L10: =VLOOKUP(A2,A1:P2,12,0) -> Weak
K11: Momentum | L11: =VLOOKUP(A2,A1:P2,13,0) -> ▲ Bullish
K12: Investor Interest | L12: =VLOOKUP(A2,A1:P2,14,0) -> High Interest
K13: Final Rating | L13: =VLOOKUP(A2,A1:P2,15,0) -> Buy
K14: Signal Type | L14: =VLOOKUP(A2,A1:P2,16,0) -> 🟡HOLD
K15: Sector | L15: =VLOOKUP(A2,A1:Q2,17,0) -> Defense Electronics
